src/__init__.py
src/load_data.py
src/main.py
src/spark_column_analyzer/__init__.py
src/spark_column_analyzer/column_analyzer.py
tests/__init__.py
tests/test_analyzer.py
spark_column_analyzer-0.2.3.dist-info/LICENSE
spark_column_analyzer-0.2.3.dist-info/METADATA
spark_column_analyzer-0.2.3.dist-info/WHEEL
spark_column_analyzer-0.2.3.dist-info/top_level.txt
spark_column_analyzer-0.2.3.dist-info/RECORD
