Metadata-Version: 2.1
Name: spark-column-analyzer
Version: 0.2.3
Summary: A package for analyzing Spark DataFrame columns
Home-page: https://github.com/michTalebzadeh/spark_column_analyzer
Author: Mich Talebzadeh
Author-email: mich.talebzadeh@gmail.com
Classifier: Development Status :: 4 - Beta
Classifier: Intended Audience :: Developers
Classifier: License :: OSI Approved :: MIT License
Classifier: Programming Language :: Python :: 3.6
Classifier: Programming Language :: Python :: 3.7
Classifier: Programming Language :: Python :: 3.8
Classifier: Programming Language :: Python :: 3.9
License-File: LICENSE
Requires-Dist: pyspark
Requires-Dist: matplotlib
Requires-Dist: numpy
Requires-Dist: seaborn
